setup.py
lpack/__init__.py
lpack/crawl.py
lpack/database.py
lpack/database2.py
lpack/log.py
lpack/parseconfig.py
lpack/test.py
lpack/useragent.py
lpack/utils.py
lpack/utils_cv.py
lpack/utils_mq.py
lpack/utils_pdf.py
lpack.egg-info/PKG-INFO
lpack.egg-info/SOURCES.txt
lpack.egg-info/dependency_links.txt
lpack.egg-info/requires.txt
lpack.egg-info/top_level.txt