Metadata-Version: 2.1
Name: lpack
Version: 3.3.0
Summary: Hello 
Home-page: 
Author: Robbe
Author-email: robbebluecp@gmail.com
Maintainer: Robbe
Maintainer-email: robbebluecp@gmail.com
License: MIT License
Platform: all
Classifier: Environment :: Web Environment
Classifier: Intended Audience :: Developers
Classifier: Operating System :: OS Independent
Classifier: Topic :: Text Processing :: Indexing
Classifier: Topic :: Utilities
Classifier: Topic :: Internet
Classifier: Topic :: Software Development :: Libraries :: Python Modules
Classifier: Programming Language :: Python
Classifier: Programming Language :: Python :: 3.7
Classifier: Programming Language :: Python :: 3.8
Classifier: Programming Language :: Python :: 3.9
